{
  "letters": [
    {
      "createdAt": "2023. 12. 1. 오후 5:13:48",
      "nickname": "된다",
      "avatar": "https://cloudflare-ipfs.com/ipfs/Qmd3W5DuhgHirLHGVixi6V76LhCkZUz6pnFt5AJBiyvHye/avatar/36.jpg",
      "content": "ㅇㅇㅇㅇㅇ된다",
      "writedTo": "Destiny Udogie",
      "id": "72148d12-ff64-ca95-7cc6-397f90bf35be"
    },
    {
      "createdAt": "2023. 12. 1. 오후 5:42:21",
      "nickname": "우도기",
      "avatar": "https://cloudflare-ipfs.com/ipfs/Qmd3W5DuhgHirLHGVixi6V76LhCkZUz6pnFt5AJBiyvHye/avatar/36.jpg",
      "content": "우도기 우도기 우도기 우도기 우도기 우도기 우도기 우도기 우도기 우도기 우도기 우도기 우도기 우도기 우도기 우도기 우도기 우도기 우도기 우도기 우도기 우도기 우도기 우도기 우도기 ",
      "writedTo": "Destiny Udogie",
      "id": "1afae195-98d3-9621-ccb5-9ddbbdd43678"
    },
    {
      "createdAt": "2023. 12. 1. 오후 5:42:28",
      "nickname": "ㅇㅇㅇㅇㅇㅇㅇㅇㅇㅇ",
      "avatar": "https://cloudflare-ipfs.com/ipfs/Qmd3W5DuhgHirLHGVixi6V76LhCkZUz6pnFt5AJBiyvHye/avatar/36.jpg",
      "content": "ㅍㅍㅍㅍㅍㅍㅍㅍㅍㅍㅍㅍㅍㅍㅍㅍㅍㅍㅍㅍㅍㅍㅍㅍㅍㅍㅍㅍㅍㅍㅍㅍㅍ",
      "writedTo": "Guglielmo Vicario",
      "id": "9ec84baa-39af-9935-092c-3c481408db93"
    },
    {
      "createdAt": "2023. 12. 2. 오후 7:43:43",
      "nickname": "안된다",
      "avatar": "https://cloudflare-ipfs.com/ipfs/Qmd3W5DuhgHirLHGVixi6V76LhCkZUz6pnFt5AJBiyvHye/avatar/36.jpg",
      "content": "왜",
      "writedTo": "Heung-Min Son",
      "id": "1f81f804-1918-0222-e377-23303a9fc683"
    },
    {
      "createdAt": "2023. 12. 3. 오후 12:32:19",
      "nickname": "ㄹㄹ",
      "avatar": "https://cloudflare-ipfs.com/ipfs/Qmd3W5DuhgHirLHGVixi6V76LhCkZUz6pnFt5AJBiyvHye/avatar/36.jpg",
      "content": "ㄹㄹㄹ",
      "writedTo": "all",
      "id": "e0b7e114-f176-8a0a-7465-8b7fe0693d13"
    }
  ]
}